libname/__init__.py
libname/abhi_hello.py
finance_calculation-0.0.1.dist-info/METADATA
finance_calculation-0.0.1.dist-info/WHEEL
finance_calculation-0.0.1.dist-info/top_level.txt
finance_calculation-0.0.1.dist-info/RECORD
