Metadata-Version: 2.1
Name: finance-calculation
Version: 0.0.1
Summary: A finance calculation package
Author: Abhishek Vyas
Author-email: abhishek.vyas@gmail.com
License: NEXT
Keywords: finance-calculation
